[{"date":"2022-03-12T15:29:34.865813+01:00","temperatureC":-13,"summary":"Sweltering","temperatureF":9},{"date":"2022-03-13T15:29:34.874128+01:00","temperatureC":37,"summary":"Scorching","temperatureF":98},{"date":"2022-03-14T15:29:34.874232+01:00","temperatureC":8,"summary":"Sweltering","temperatureF":46},{"date":"2022-03-15T15:29:34.874244+01:00","temperatureC":20,"summary":"Balmy","temperatureF":67},{"date":"2022-03-16T15:29:34.874248+01:00","temperatureC":35,"summary":"Warm","temperatureF":94}]